RecF64ToF64/Equiv_RecF64ToF64.v
module Equiv_RecF64ToF64(
    input [64:0] io_in,
    output[63:0] io_out,
    output io_isBadNaN,
    output[2:0] io_firstThree,
    output[52:0] io_sig,
    output[52:0] io_compare
);

  wire[52:0] T0;
  wire[2:0] T1;
  wire T2;
  wire T3;
  wire[52:0] T4;
  wire T5;
  wire[2:0] T6;
  wire[63:0] T7;
  wire[62:0] T8;
  wire[51:0] T9;
  wire[51:0] T10;
  wire[51:0] T11;
  wire[53:0] T12;
  wire[53:0] T13;
  wire[52:0] T14;
  wire[51:0] T15;
  wire T16;
  wire T17;
  wire[2:0] T18;
  wire[11:0] T19;
  wire T20;
  wire T21;
  wire T22;
  wire T23;
  wire T24;
  wire[1:0] T25;
  wire[51:0] T26;
  wire[52:0] T27;
  wire[5:0] T28;
  wire[5:0] T29;
  wire[12:0] T30;
  wire[12:0] T31;
  wire[12:0] T32;
  wire[52:0] T33;
  wire T34;
  wire[10:0] T35;
  wire[10:0] T36;
  wire[10:0] T46;
  wire T37;
  wire T38;
  wire T39;
  wire T40;
  wire[10:0] T41;
  wire[10:0] T42;
  wire[10:0] T43;
  wire T44;
  wire T45;


  assign io_compare = 53'h1fffffffffffff;
  assign io_sig = T0;
  assign T0 = io_in[52:0];
  assign io_firstThree = T1;
  assign T1 = io_in[63:61];
  assign io_isBadNaN = T2;
  assign T2 = T5 & T3;
  assign T3 = T4 != 53'h1fffffffffffff;
  assign T4 = io_in[52:0];
  assign T5 = T6 == 3'h7;
  assign T6 = io_in[63:61];
  assign io_out = T7;
  assign T7 = {T44, T8};
  assign T8 = {T35, T9};
  assign T9 = T34 ? T26 : T10;
  assign T10 = T20 ? 52'h0 : T11;
  assign T11 = T12[51:0];
  assign T12 = T13;
  assign T13 = {1'h0, T14};
  assign T14 = {T16, T15};
  assign T15 = io_in[51:0];
  assign T16 = T17 ^ 1'h1;
  assign T17 = T18 == 3'h0;
  assign T18 = T19[11:9];
  assign T19 = io_in[63:52];
  assign T20 = T21;
  assign T21 = T24 & T22;
  assign T22 = T23 ^ 1'h1;
  assign T23 = T19[9];
  assign T24 = T25 == 2'h3;
  assign T25 = T19[11:10];
  assign T26 = T27[51:0];
  assign T27 = T33 >> T28;
  assign T28 = 6'h1 - T29;
  assign T29 = T30[5:0];
  assign T30 = T31;
  assign T31 = T32;
  assign T32 = {1'h0, T19};
  assign T33 = T12 >> 1'h1;
  assign T34 = $signed(T30) < $signed(12'h402);
  assign T35 = T41 | T36;
  assign T36 = 11'h0 - T46;
  assign T46 = {10'h0, T37};
  assign T37 = T38 | T20;
  assign T38 = T39;
  assign T39 = T24 & T40;
  assign T40 = T19[9];
  assign T41 = T34 ? 11'h0 : T42;
  assign T42 = T43 - 11'h401;
  assign T43 = T30[10:0];
  assign T44 = T45;
  assign T45 = io_in[64];
endmodule

RecF64ToF64/trace.vcd
$version Generated by VerilatedVcd $end
$date Wed Jun  6 13:42:53 2018
 $end
$timescale   1ns $end

 $scope module TOP $end
  $var wire 53 7 io_compare [52:0] $end
  $var wire  3 4 io_firstThree [2:0] $end
  $var wire 65 . io_in [64:0] $end
  $var wire  1 3 io_isBadNaN $end
  $var wire 64 1 io_out [63:0] $end
  $var wire 53 5 io_sig [52:0] $end
  $scope module Equiv_RecF64ToF64 $end
   $var wire 53 9 T0 [52:0] $end
   $var wire  3 ; T1 [2:0] $end
   $var wire 52 # T10 [51:0] $end
   $var wire 52 % T11 [51:0] $end
   $var wire 54 ' T12 [53:0] $end
   $var wire 54 ' T13 [53:0] $end
   $var wire 53 ) T14 [52:0] $end
   $var wire 52 E T15 [51:0] $end
   $var wire  1 G T16 $end
   $var wire  1 H T17 $end
   $var wire  3 I T18 [2:0] $end
   $var wire 12 J T19 [11:0] $end
   $var wire  1 < T2 $end
   $var wire  1 + T20 $end
   $var wire  1 + T21 $end
   $var wire  1 K T22 $end
   $var wire  1 L T23 $end
   $var wire  1 M T24 $end
   $var wire  2 N T25 [1:0] $end
   $var wire 52 O T26 [51:0] $end
   $var wire 53 Q T27 [52:0] $end
   $var wire  6 S T28 [5:0] $end
   $var wire  6 T T29 [5:0] $end
   $var wire  1 = T3 $end
   $var wire 13 U T30 [12:0] $end
   $var wire 13 U T31 [12:0] $end
   $var wire 13 U T32 [12:0] $end
   $var wire 53 , T33 [52:0] $end
   $var wire  1 V T34 $end
   $var wire 11 W T35 [10:0] $end
   $var wire 11 X T36 [10:0] $end
   $var wire  1 Z T37 $end
   $var wire  1 [ T38 $end
   $var wire  1 [ T39 $end
   $var wire 53 9 T4 [52:0] $end
   $var wire  1 L T40 $end
   $var wire 11 \ T41 [10:0] $end
   $var wire 11 ] T42 [10:0] $end
   $var wire 11 ^ T43 [10:0] $end
   $var wire  1 _ T44 $end
   $var wire  1 _ T45 $end
   $var wire 11 Y T46 [10:0] $end
   $var wire  1 > T5 $end
   $var wire  3 ; T6 [2:0] $end
   $var wire 64 ? T7 [63:0] $end
   $var wire 63 A T8 [62:0] $end
   $var wire 52 C T9 [51:0] $end
   $var wire 53 7 io_compare [52:0] $end
   $var wire  3 4 io_firstThree [2:0] $end
   $var wire 65 . io_in [64:0] $end
   $var wire  1 3 io_isBadNaN $end
   $var wire 64 1 io_out [63:0] $end
   $var wire 53 5 io_sig [52:0] $end
  $upscope $end
 $upscope $end
$enddefinitions $end


#0
b1111111111111111111111111111111111111111111111111111 #
b1111111111111111111111111111111111111111111111111111 %
b011111111111111111111111111111111111111111111111111111 '
b11111111111111111111111111111111111111111111111111111 )
0+
b01111111111111111111111111111111111111111111111111111 ,
b00110101000001111111111111111111111111111111111111111111111111111 .
b0010100111111111111111111111111111111111111111111111111111111111 1
03
b011 4
b01111111111111111111111111111111111111111111111111111 5
b11111111111111111111111111111111111111111111111111111 7
b01111111111111111111111111111111111111111111111111111 9
b011 ;
0<
1=
0>
b0010100111111111111111111111111111111111111111111111111111111111 ?
b010100111111111111111111111111111111111111111111111111111111111 A
b1111111111111111111111111111111111111111111111111111 C
b1111111111111111111111111111111111111111111111111111 E
1G
0H
b011 I
b011010100000 J
0K
1L
0M
b01 N
b0000000000000000000000000000000001111111111111111111 O
b00000000000000000000000000000000001111111111111111111 Q
b100001 S
b100000 T
b0011010100000 U
0V
b01010011111 W
b00000000000 X
b00000000000 Y
0Z
0[
b01010011111 \
b01010011111 ]
b11010100000 ^
0_
#1
b00110100111111111111111111111111111111111111111111111111111111111 .
b0010100111101111111111111111111111111111111111111111111111111111 1
b11111111111111111111111111111111111111111111111111111 5
b11111111111111111111111111111111111111111111111111111 9
0=
b0010100111101111111111111111111111111111111111111111111111111111 ?
b010100111101111111111111111111111111111111111111111111111111111 A
b011010011111 J
b0000000000000000000000000000000000111111111111111111 O
b00000000000000000000000000000000000111111111111111111 Q
b100010 S
b011111 T
b0011010011111 U
b01010011110 W
b01010011110 \
b01010011110 ]
b11010011111 ^
#2
b00110100111101111111111111111111111111111111111111111111111111111 .
b0010100111011111111111111111111111111111111111111111111111111111 1
b01111111111111111111111111111111111111111111111111111 5
b01111111111111111111111111111111111111111111111111111 9
1=
b0010100111011111111111111111111111111111111111111111111111111111 ?
b010100111011111111111111111111111111111111111111111111111111111 A
b011010011110 J
b0000000000000000000000000000000000011111111111111111 O
b00000000000000000000000000000000000011111111111111111 Q
b100011 S
b011110 T
b0011010011110 U
b01010011101 W
b01010011101 \
b01010011101 ]
b11010011110 ^
#3
b00110100111011111111111111111111111111111111111111111111111111111 .
b0010100111001111111111111111111111111111111111111111111111111111 1
b11111111111111111111111111111111111111111111111111111 5
b11111111111111111111111111111111111111111111111111111 9
0=
b0010100111001111111111111111111111111111111111111111111111111111 ?
b010100111001111111111111111111111111111111111111111111111111111 A
b011010011101 J
b0000000000000000000000000000000000001111111111111111 O
b00000000000000000000000000000000000001111111111111111 Q
b100100 S
b011101 T
b0011010011101 U
b01010011100 W
b01010011100 \
b01010011100 ]
b11010011101 ^
#4
b00110100111001111111111111111111111111111111111111111111111111111 .
b0010100110111111111111111111111111111111111111111111111111111111 1
b01111111111111111111111111111111111111111111111111111 5
b01111111111111111111111111111111111111111111111111111 9
1=
b0010100110111111111111111111111111111111111111111111111111111111 ?
b010100110111111111111111111111111111111111111111111111111111111 A
b011010011100 J
b0000000000000000000000000000000000000111111111111111 O
b00000000000000000000000000000000000000111111111111111 Q
b100101 S
b011100 T
b0011010011100 U
b01010011011 W
b01010011011 \
b01010011011 ]
b11010011100 ^
#5
b00110100110111111111111111111111111111111111111111111111111111111 .
b0010100110101111111111111111111111111111111111111111111111111111 1
b11111111111111111111111111111111111111111111111111111 5
b11111111111111111111111111111111111111111111111111111 9
0=
b0010100110101111111111111111111111111111111111111111111111111111 ?
b010100110101111111111111111111111111111111111111111111111111111 A
b011010011011 J
b0000000000000000000000000000000000000011111111111111 O
b00000000000000000000000000000000000000011111111111111 Q
b100110 S
b011011 T
b0011010011011 U
b01010011010 W
b01010011010 \
b01010011010 ]
b11010011011 ^
#6
b00110100110101111111111111111111111111111111111111111111111111111 .
b0010100110011111111111111111111111111111111111111111111111111111 1
b01111111111111111111111111111111111111111111111111111 5
b01111111111111111111111111111111111111111111111111111 9
1=
b0010100110011111111111111111111111111111111111111111111111111111 ?
b010100110011111111111111111111111111111111111111111111111111111 A
b011010011010 J
b0000000000000000000000000000000000000001111111111111 O
b00000000000000000000000000000000000000001111111111111 Q
b100111 S
b011010 T
b0011010011010 U
b01010011001 W
b01010011001 \
b01010011001 ]
b11010011010 ^
#7
b00110100110011111111111111111111111111111111111111111111111111111 .
b0010100110001111111111111111111111111111111111111111111111111111 1
b11111111111111111111111111111111111111111111111111111 5
b11111111111111111111111111111111111111111111111111111 9
0=
b0010100110001111111111111111111111111111111111111111111111111111 ?
b010100110001111111111111111111111111111111111111111111111111111 A
b011010011001 J
b0000000000000000000000000000000000000000111111111111 O
b00000000000000000000000000000000000000000111111111111 Q
b101000 S
b011001 T
b0011010011001 U
b01010011000 W
b01010011000 \
b01010011000 ]
b11010011001 ^
#8
b00110100110001111111111111111111111111111111111111111111111111111 .
b0010100101111111111111111111111111111111111111111111111111111111 1
b01111111111111111111111111111111111111111111111111111 5
b01111111111111111111111111111111111111111111111111111 9
1=
b0010100101111111111111111111111111111111111111111111111111111111 ?
b010100101111111111111111111111111111111111111111111111111111111 A
b011010011000 J
b0000000000000000000000000000000000000000011111111111 O
b00000000000000000000000000000000000000000011111111111 Q
b101001 S
b011000 T
b0011010011000 U
b01010010111 W
b01010010111 \
b01010010111 ]
b11010011000 ^
#9
b00110100101111111111111111111111111111111111111111111111111111111 .
b0010100101101111111111111111111111111111111111111111111111111111 1
b11111111111111111111111111111111111111111111111111111 5
b11111111111111111111111111111111111111111111111111111 9
0=
b0010100101101111111111111111111111111111111111111111111111111111 ?
b010100101101111111111111111111111111111111111111111111111111111 A
b011010010111 J
b0000000000000000000000000000000000000000001111111111 O
b00000000000000000000000000000000000000000001111111111 Q
b101010 S
b010111 T
b0011010010111 U
b01010010110 W
b01010010110 \
b01010010110 ]
b11010010111 ^
#10
b00110100101101111111111111111111111111111111111111111111111111111 .
b0010100101011111111111111111111111111111111111111111111111111111 1
b01111111111111111111111111111111111111111111111111111 5
b01111111111111111111111111111111111111111111111111111 9
1=
b0010100101011111111111111111111111111111111111111111111111111111 ?
b010100101011111111111111111111111111111111111111111111111111111 A
b011010010110 J
b0000000000000000000000000000000000000000000111111111 O
b00000000000000000000000000000000000000000000111111111 Q
b101011 S
b010110 T
b0011010010110 U
b01010010101 W
b01010010101 \
b01010010101 ]
b11010010110 ^
#11
b00110100101011111111111111111111111111111111111111111111111111111 .
b0010100101001111111111111111111111111111111111111111111111111111 1
b11111111111111111111111111111111111111111111111111111 5
b11111111111111111111111111111111111111111111111111111 9
0=
b0010100101001111111111111111111111111111111111111111111111111111 ?
b010100101001111111111111111111111111111111111111111111111111111 A
b011010010101 J
b0000000000000000000000000000000000000000000011111111 O
b00000000000000000000000000000000000000000000011111111 Q
b101100 S
b010101 T
b0011010010101 U
b01010010100 W
b01010010100 \
b01010010100 ]
b11010010101 ^
#12
b00110100101001111111111111111111111111111111111111111111111111111 .
b0010100100111111111111111111111111111111111111111111111111111111 1
b01111111111111111111111111111111111111111111111111111 5
b01111111111111111111111111111111111111111111111111111 9
1=
b0010100100111111111111111111111111111111111111111111111111111111 ?
b010100100111111111111111111111111111111111111111111111111111111 A
b011010010100 J
b0000000000000000000000000000000000000000000001111111 O
b00000000000000000000000000000000000000000000001111111 Q
b101101 S
b010100 T
b0011010010100 U
b01010010011 W
b01010010011 \
b01010010011 ]
b11010010100 ^
#13
b00110100100111111111111111111111111111111111111111111111111111111 .
b0010100100101111111111111111111111111111111111111111111111111111 1
b11111111111111111111111111111111111111111111111111111 5
b11111111111111111111111111111111111111111111111111111 9
0=
b0010100100101111111111111111111111111111111111111111111111111111 ?
b010100100101111111111111111111111111111111111111111111111111111 A
b011010010011 J
b0000000000000000000000000000000000000000000000111111 O
b00000000000000000000000000000000000000000000000111111 Q
b101110 S
b010011 T
b0011010010011 U
b01010010010 W
b01010010010 \
b01010010010 ]
b11010010011 ^
#14
b00110100100101111111111111111111111111111111111111111111111111111 .
b0010100100011111111111111111111111111111111111111111111111111111 1
b01111111111111111111111111111111111111111111111111111 5
b01111111111111111111111111111111111111111111111111111 9
1=
b0010100100011111111111111111111111111111111111111111111111111111 ?
b010100100011111111111111111111111111111111111111111111111111111 A
b011010010010 J
b0000000000000000000000000000000000000000000000011111 O
b00000000000000000000000000000000000000000000000011111 Q
b101111 S
b010010 T
b0011010010010 U
b01010010001 W
b01010010001 \
b01010010001 ]
b11010010010 ^
#15
b00110100100011111111111111111111111111111111111111111111111111111 .
b0010100100001111111111111111111111111111111111111111111111111111 1
b11111111111111111111111111111111111111111111111111111 5
b11111111111111111111111111111111111111111111111111111 9
0=
b0010100100001111111111111111111111111111111111111111111111111111 ?
b010100100001111111111111111111111111111111111111111111111111111 A
b011010010001 J
b0000000000000000000000000000000000000000000000001111 O
b00000000000000000000000000000000000000000000000001111 Q
b110000 S
b010001 T
b0011010010001 U
b01010010000 W
b01010010000 \
b01010010000 ]
b11010010001 ^
#16
b00110100100001111111111111111111111111111111111111111111111111111 .
b0010100011111111111111111111111111111111111111111111111111111111 1
b01111111111111111111111111111111111111111111111111111 5
b01111111111111111111111111111111111111111111111111111 9
1=
b0010100011111111111111111111111111111111111111111111111111111111 ?
b010100011111111111111111111111111111111111111111111111111111111 A
b011010010000 J
b0000000000000000000000000000000000000000000000000111 O
b00000000000000000000000000000000000000000000000000111 Q
b110001 S
b010000 T
b0011010010000 U
b01010001111 W
b01010001111 \
b01010001111 ]
b11010010000 ^
#17
b00110100011111111111111111111111111111111111111111111111111111111 .
b0010100011101111111111111111111111111111111111111111111111111111 1
b11111111111111111111111111111111111111111111111111111 5
b11111111111111111111111111111111111111111111111111111 9
0=
b0010100011101111111111111111111111111111111111111111111111111111 ?
b010100011101111111111111111111111111111111111111111111111111111 A
b011010001111 J
b0000000000000000000000000000000000000000000000000011 O
b00000000000000000000000000000000000000000000000000011 Q
b110010 S
b001111 T
b0011010001111 U
b01010001110 W
b01010001110 \
b01010001110 ]
b11010001111 ^
#18
b00110100011101111111111111111111111111111111111111111111111111111 .
b0010100011011111111111111111111111111111111111111111111111111111 1
b01111111111111111111111111111111111111111111111111111 5
b01111111111111111111111111111111111111111111111111111 9
1=
b0010100011011111111111111111111111111111111111111111111111111111 ?
b010100011011111111111111111111111111111111111111111111111111111 A
b011010001110 J
b0000000000000000000000000000000000000000000000000001 O
b00000000000000000000000000000000000000000000000000001 Q
b110011 S
b001110 T
b0011010001110 U
b01010001101 W
b01010001101 \
b01010001101 ]
b11010001110 ^
#19
b00110100011011111111111111111111111111111111111111111111111111111 .
b0010100011001111111111111111111111111111111111111111111111111111 1
b11111111111111111111111111111111111111111111111111111 5
b11111111111111111111111111111111111111111111111111111 9
0=
b0010100011001111111111111111111111111111111111111111111111111111 ?
b010100011001111111111111111111111111111111111111111111111111111 A
b011010001101 J
b0000000000000000000000000000000000000000000000000000 O
b00000000000000000000000000000000000000000000000000000 Q
b110100 S
b001101 T
b0011010001101 U
b01010001100 W
b01010001100 \
b01010001100 ]
b11010001101 ^
#20
b00110100011001111111111111111111111111111111111111111111111111111 .
b0010100010111111111111111111111111111111111111111111111111111111 1
b01111111111111111111111111111111111111111111111111111 5
b01111111111111111111111111111111111111111111111111111 9
1=
b0010100010111111111111111111111111111111111111111111111111111111 ?
b010100010111111111111111111111111111111111111111111111111111111 A
b011010001100 J
b110101 S
b001100 T
b0011010001100 U
b01010001011 W
b01010001011 \
b01010001011 ]
b11010001100 ^
#21
b00110100010111111111111111111111111111111111111111111111111111111 .
b0010100010101111111111111111111111111111111111111111111111111111 1
b11111111111111111111111111111111111111111111111111111 5
b11111111111111111111111111111111111111111111111111111 9
0=
b0010100010101111111111111111111111111111111111111111111111111111 ?
b010100010101111111111111111111111111111111111111111111111111111 A
b011010001011 J
b110110 S
b001011 T
b0011010001011 U
b01010001010 W
b01010001010 \
b01010001010 ]
b11010001011 ^
#22
b00110100010101111111111111111111111111111111111111111111111111111 .
b0010100010011111111111111111111111111111111111111111111111111111 1
b01111111111111111111111111111111111111111111111111111 5
b01111111111111111111111111111111111111111111111111111 9
1=
b0010100010011111111111111111111111111111111111111111111111111111 ?
b010100010011111111111111111111111111111111111111111111111111111 A
b011010001010 J
b110111 S
b001010 T
b0011010001010 U
b01010001001 W
b01010001001 \
b01010001001 ]
b11010001010 ^
#23
b00110100010011111111111111111111111111111111111111111111111111111 .
b0010100010001111111111111111111111111111111111111111111111111111 1
b11111111111111111111111111111111111111111111111111111 5
b11111111111111111111111111111111111111111111111111111 9
0=
b0010100010001111111111111111111111111111111111111111111111111111 ?
b010100010001111111111111111111111111111111111111111111111111111 A
b011010001001 J
b111000 S
b001001 T
b0011010001001 U
b01010001000 W
b01010001000 \
b01010001000 ]
b11010001001 ^
#24
b00110100010001111111111111111111111111111111111111111111111111111 .
b0010100001111111111111111111111111111111111111111111111111111111 1
b01111111111111111111111111111111111111111111111111111 5
b01111111111111111111111111111111111111111111111111111 9
1=
b0010100001111111111111111111111111111111111111111111111111111111 ?
b010100001111111111111111111111111111111111111111111111111111111 A
b011010001000 J
b111001 S
b001000 T
b0011010001000 U
b01010000111 W
b01010000111 \
b01010000111 ]
b11010001000 ^
#25
b00110100001111111111111111111111111111111111111111111111111111111 .
b0010100001101111111111111111111111111111111111111111111111111111 1
b11111111111111111111111111111111111111111111111111111 5
b11111111111111111111111111111111111111111111111111111 9
0=
b0010100001101111111111111111111111111111111111111111111111111111 ?
b010100001101111111111111111111111111111111111111111111111111111 A
b011010000111 J
b111010 S
b000111 T
b0011010000111 U
b01010000110 W
b01010000110 \
b01010000110 ]
b11010000111 ^
#26
b00110100001101111111111111111111111111111111111111111111111111111 .
b0010100001011111111111111111111111111111111111111111111111111111 1
b01111111111111111111111111111111111111111111111111111 5
b01111111111111111111111111111111111111111111111111111 9
1=
b0010100001011111111111111111111111111111111111111111111111111111 ?
b010100001011111111111111111111111111111111111111111111111111111 A
b011010000110 J
b111011 S
b000110 T
b0011010000110 U
b01010000101 W
b01010000101 \
b01010000101 ]
b11010000110 ^
#27
b00110100001011111111111111111111111111111111111111111111111111111 .
b0010100001001111111111111111111111111111111111111111111111111111 1
b11111111111111111111111111111111111111111111111111111 5
b11111111111111111111111111111111111111111111111111111 9
0=
b0010100001001111111111111111111111111111111111111111111111111111 ?
b010100001001111111111111111111111111111111111111111111111111111 A
b011010000101 J
b111100 S
b000101 T
b0011010000101 U
b01010000100 W
b01010000100 \
b01010000100 ]
b11010000101 ^
#28
b00110100001001111111111111111111111111111111111111111111111111111 .
b0010100000111111111111111111111111111111111111111111111111111111 1
b01111111111111111111111111111111111111111111111111111 5
b01111111111111111111111111111111111111111111111111111 9
1=
b0010100000111111111111111111111111111111111111111111111111111111 ?
b010100000111111111111111111111111111111111111111111111111111111 A
b011010000100 J
b111101 S
b000100 T
b0011010000100 U
b01010000011 W
b01010000011 \
b01010000011 ]
b11010000100 ^
#29
b00110100000111111111111111111111111111111111111111111111111111111 .
b0010100000101111111111111111111111111111111111111111111111111111 1
b11111111111111111111111111111111111111111111111111111 5
b11111111111111111111111111111111111111111111111111111 9
0=
b0010100000101111111111111111111111111111111111111111111111111111 ?
b010100000101111111111111111111111111111111111111111111111111111 A
b011010000011 J
b111110 S
b000011 T
b0011010000011 U
b01010000010 W
b01010000010 \
b01010000010 ]
b11010000011 ^
#30
b00110100000101111111111111111111111111111111111111111111111111111 .
b0010100000011111111111111111111111111111111111111111111111111111 1
b01111111111111111111111111111111111111111111111111111 5
b01111111111111111111111111111111111111111111111111111 9
1=
b0010100000011111111111111111111111111111111111111111111111111111 ?
b010100000011111111111111111111111111111111111111111111111111111 A
b011010000010 J
b111111 S
b000010 T
b0011010000010 U
b01010000001 W
b01010000001 \
b01010000001 ]
b11010000010 ^
#31
b00110100000011111111111111111111111111111111111111111111111111111 .
b0010100000001111111111111111111111111111111111111111111111111111 1
b11111111111111111111111111111111111111111111111111111 5
b11111111111111111111111111111111111111111111111111111 9
0=
b0010100000001111111111111111111111111111111111111111111111111111 ?
b010100000001111111111111111111111111111111111111111111111111111 A
b011010000001 J
b1111111111111111111111111111111111111111111111111111 O
b01111111111111111111111111111111111111111111111111111 Q
b000000 S
b000001 T
b0011010000001 U
b01010000000 W
b01010000000 \
b01010000000 ]
b11010000001 ^
#32
b00110100000001111111111111111111111111111111111111111111111111111 .
b0010011111111111111111111111111111111111111111111111111111111111 1
b01111111111111111111111111111111111111111111111111111 5
b01111111111111111111111111111111111111111111111111111 9
1=
b0010011111111111111111111111111111111111111111111111111111111111 ?
b010011111111111111111111111111111111111111111111111111111111111 A
b011010000000 J
b0111111111111111111111111111111111111111111111111111 O
b00111111111111111111111111111111111111111111111111111 Q
b000001 S
b000000 T
b0011010000000 U
b01001111111 W
b01001111111 \
b01001111111 ]
b11010000000 ^
#33
b00110011111111111111111111111111111111111111111111111111111111111 .
b0010011111101111111111111111111111111111111111111111111111111111 1
b11111111111111111111111111111111111111111111111111111 5
b11111111111111111111111111111111111111111111111111111 9
0=
b0010011111101111111111111111111111111111111111111111111111111111 ?
b010011111101111111111111111111111111111111111111111111111111111 A
b011001111111 J
b0011111111111111111111111111111111111111111111111111 O
b00011111111111111111111111111111111111111111111111111 Q
b000010 S
b111111 T
b0011001111111 U
b01001111110 W
b01001111110 \
b01001111110 ]
b11001111111 ^
#34
b00110011111101111111111111111111111111111111111111111111111111111 .
b0010011111011111111111111111111111111111111111111111111111111111 1
b01111111111111111111111111111111111111111111111111111 5
b01111111111111111111111111111111111111111111111111111 9
1=
b0010011111011111111111111111111111111111111111111111111111111111 ?
b010011111011111111111111111111111111111111111111111111111111111 A
b011001111110 J
b0001111111111111111111111111111111111111111111111111 O
b00001111111111111111111111111111111111111111111111111 Q
b000011 S
b111110 T
b0011001111110 U
b01001111101 W
b01001111101 \
b01001111101 ]
b11001111110 ^
#35
b00110011111011111111111111111111111111111111111111111111111111111 .
b0010011111001111111111111111111111111111111111111111111111111111 1
b11111111111111111111111111111111111111111111111111111 5
b11111111111111111111111111111111111111111111111111111 9
0=
b0010011111001111111111111111111111111111111111111111111111111111 ?
b010011111001111111111111111111111111111111111111111111111111111 A
b011001111101 J
b0000111111111111111111111111111111111111111111111111 O
b00000111111111111111111111111111111111111111111111111 Q
b000100 S
b111101 T
b0011001111101 U
b01001111100 W
b01001111100 \
b01001111100 ]
b11001111101 ^
#36
b00110011111001111111111111111111111111111111111111111111111111111 .
b0010011110111111111111111111111111111111111111111111111111111111 1
b01111111111111111111111111111111111111111111111111111 5
b01111111111111111111111111111111111111111111111111111 9
1=
b0010011110111111111111111111111111111111111111111111111111111111 ?
b010011110111111111111111111111111111111111111111111111111111111 A
b011001111100 J
b0000011111111111111111111111111111111111111111111111 O
b00000011111111111111111111111111111111111111111111111 Q
b000101 S
b111100 T
b0011001111100 U
b01001111011 W
b01001111011 \
b01001111011 ]
b11001111100 ^
#37
b00110011110111111111111111111111111111111111111111111111111111111 .
b0010011110101111111111111111111111111111111111111111111111111111 1
b11111111111111111111111111111111111111111111111111111 5
b11111111111111111111111111111111111111111111111111111 9
0=
b0010011110101111111111111111111111111111111111111111111111111111 ?
b010011110101111111111111111111111111111111111111111111111111111 A
b011001111011 J
b0000001111111111111111111111111111111111111111111111 O
b00000001111111111111111111111111111111111111111111111 Q
b000110 S
b111011 T
b0011001111011 U
b01001111010 W
b01001111010 \
b01001111010 ]
b11001111011 ^
#38
b00110011110101111111111111111111111111111111111111111111111111111 .
b0010011110011111111111111111111111111111111111111111111111111111 1
b01111111111111111111111111111111111111111111111111111 5
b01111111111111111111111111111111111111111111111111111 9
1=
b0010011110011111111111111111111111111111111111111111111111111111 ?
b010011110011111111111111111111111111111111111111111111111111111 A
b011001111010 J
b0000000111111111111111111111111111111111111111111111 O
b00000000111111111111111111111111111111111111111111111 Q
b000111 S
b111010 T
b0011001111010 U
b01001111001 W
b01001111001 \
b01001111001 ]
b11001111010 ^
#39
b00110011110011111111111111111111111111111111111111111111111111111 .
b0010011110001111111111111111111111111111111111111111111111111111 1
b11111111111111111111111111111111111111111111111111111 5
b11111111111111111111111111111111111111111111111111111 9
0=
b0010011110001111111111111111111111111111111111111111111111111111 ?
b010011110001111111111111111111111111111111111111111111111111111 A
b011001111001 J
b0000000011111111111111111111111111111111111111111111 O
b00000000011111111111111111111111111111111111111111111 Q
b001000 S
b111001 T
b0011001111001 U
b01001111000 W
b01001111000 \
b01001111000 ]
b11001111001 ^
#40
b00110011110001111111111111111111111111111111111111111111111111111 .
b0010011101111111111111111111111111111111111111111111111111111111 1
b01111111111111111111111111111111111111111111111111111 5
b01111111111111111111111111111111111111111111111111111 9
1=
b0010011101111111111111111111111111111111111111111111111111111111 ?
b010011101111111111111111111111111111111111111111111111111111111 A
b011001111000 J
b0000000001111111111111111111111111111111111111111111 O
b00000000001111111111111111111111111111111111111111111 Q
b001001 S
b111000 T
b0011001111000 U
b01001110111 W
b01001110111 \
b01001110111 ]
b11001111000 ^
#41
b00110011101111111111111111111111111111111111111111111111111111111 .
b0010011101101111111111111111111111111111111111111111111111111111 1
b11111111111111111111111111111111111111111111111111111 5
b11111111111111111111111111111111111111111111111111111 9
0=
b0010011101101111111111111111111111111111111111111111111111111111 ?
b010011101101111111111111111111111111111111111111111111111111111 A
b011001110111 J
b0000000000111111111111111111111111111111111111111111 O
b00000000000111111111111111111111111111111111111111111 Q
b001010 S
b110111 T
b0011001110111 U
b01001110110 W
b01001110110 \
b01001110110 ]
b11001110111 ^
#42
b00110011101101111111111111111111111111111111111111111111111111111 .
b0010011101011111111111111111111111111111111111111111111111111111 1
b01111111111111111111111111111111111111111111111111111 5
b01111111111111111111111111111111111111111111111111111 9
1=
b0010011101011111111111111111111111111111111111111111111111111111 ?
b010011101011111111111111111111111111111111111111111111111111111 A
b011001110110 J
b0000000000011111111111111111111111111111111111111111 O
b00000000000011111111111111111111111111111111111111111 Q
b001011 S
b110110 T
b0011001110110 U
b01001110101 W
b01001110101 \
b01001110101 ]
b11001110110 ^
#43
b00110011101011111111111111111111111111111111111111111111111111111 .
b0010011101001111111111111111111111111111111111111111111111111111 1
b11111111111111111111111111111111111111111111111111111 5
b11111111111111111111111111111111111111111111111111111 9
0=
b0010011101001111111111111111111111111111111111111111111111111111 ?
b010011101001111111111111111111111111111111111111111111111111111 A
b011001110101 J
b0000000000001111111111111111111111111111111111111111 O
b00000000000001111111111111111111111111111111111111111 Q
b001100 S
b110101 T
b0011001110101 U
b01001110100 W
b01001110100 \
b01001110100 ]
b11001110101 ^
#44
b00110011101001111111111111111111111111111111111111111111111111111 .
b0010011100111111111111111111111111111111111111111111111111111111 1
b01111111111111111111111111111111111111111111111111111 5
b01111111111111111111111111111111111111111111111111111 9
1=
b0010011100111111111111111111111111111111111111111111111111111111 ?
b010011100111111111111111111111111111111111111111111111111111111 A
b011001110100 J
b0000000000000111111111111111111111111111111111111111 O
b00000000000000111111111111111111111111111111111111111 Q
b001101 S
b110100 T
b0011001110100 U
b01001110011 W
b01001110011 \
b01001110011 ]
b11001110100 ^
#45
b00110011100111111111111111111111111111111111111111111111111111111 .
b0010011100101111111111111111111111111111111111111111111111111111 1
b11111111111111111111111111111111111111111111111111111 5
b11111111111111111111111111111111111111111111111111111 9
0=
b0010011100101111111111111111111111111111111111111111111111111111 ?
b010011100101111111111111111111111111111111111111111111111111111 A
b011001110011 J
b0000000000000011111111111111111111111111111111111111 O
b00000000000000011111111111111111111111111111111111111 Q
b001110 S
b110011 T
b0011001110011 U
b01001110010 W
b01001110010 \
b01001110010 ]
b11001110011 ^
#46
b00110011100101111111111111111111111111111111111111111111111111111 .
b0010011100011111111111111111111111111111111111111111111111111111 1
b01111111111111111111111111111111111111111111111111111 5
b01111111111111111111111111111111111111111111111111111 9
1=
b0010011100011111111111111111111111111111111111111111111111111111 ?
b010011100011111111111111111111111111111111111111111111111111111 A
b011001110010 J
b0000000000000001111111111111111111111111111111111111 O
b00000000000000001111111111111111111111111111111111111 Q
b001111 S
b110010 T
b0011001110010 U
b01001110001 W
b01001110001 \
b01001110001 ]
b11001110010 ^
