RecF32ToF32/Equiv_RecF32ToF32.v
module Equiv_RecF32ToF32(
    input [32:0] io_in,
    output[31:0] io_out,
    output io_isBadNaN,
    output[2:0] io_firstThree,
    output[23:0] io_sig,
    output[23:0] io_compare
);

  wire[23:0] T0;
  wire[2:0] T1;
  wire T2;
  wire T3;
  wire[23:0] T4;
  wire T5;
  wire[2:0] T6;
  wire[31:0] T7;
  wire[30:0] T8;
  wire[22:0] T9;
  wire[22:0] T10;
  wire[22:0] T11;
  wire[24:0] T12;
  wire[24:0] T13;
  wire[23:0] T14;
  wire[22:0] T15;
  wire T16;
  wire T17;
  wire[2:0] T18;
  wire[8:0] T19;
  wire T20;
  wire T21;
  wire T22;
  wire T23;
  wire T24;
  wire[1:0] T25;
  wire[22:0] T26;
  wire[23:0] T27;
  wire[4:0] T28;
  wire[4:0] T29;
  wire[9:0] T30;
  wire[9:0] T31;
  wire[9:0] T32;
  wire[23:0] T33;
  wire T34;
  wire[7:0] T35;
  wire[7:0] T36;
  wire[7:0] T46;
  wire T37;
  wire T38;
  wire T39;
  wire T40;
  wire[7:0] T41;
  wire[7:0] T42;
  wire[7:0] T43;
  wire T44;
  wire T45;


  assign io_compare = 24'hffffff;
  assign io_sig = T0;
  assign T0 = io_in[23:0];
  assign io_firstThree = T1;
  assign T1 = io_in[31:29];
  assign io_isBadNaN = T2;
  assign T2 = T5 & T3;
  assign T3 = T4 != 24'hffffff;
  assign T4 = io_in[23:0];
  assign T5 = T6 == 3'h7;
  assign T6 = io_in[31:29];
  assign io_out = T7;
  assign T7 = {T44, T8};
  assign T8 = {T35, T9};
  assign T9 = T34 ? T26 : T10;
  assign T10 = T20 ? 23'h0 : T11;
  assign T11 = T12[22:0];
  assign T12 = T13;
  assign T13 = {1'h0, T14};
  assign T14 = {T16, T15};
  assign T15 = io_in[22:0];
  assign T16 = T17 ^ 1'h1;
  assign T17 = T18 == 3'h0;
  assign T18 = T19[8:6];
  assign T19 = io_in[31:23];
  assign T20 = T21;
  assign T21 = T24 & T22;
  assign T22 = T23 ^ 1'h1;
  assign T23 = T19[6];
  assign T24 = T25 == 2'h3;
  assign T25 = T19[8:7];
  assign T26 = T27[22:0];
  assign T27 = T33 >> T28;
  assign T28 = 5'h1 - T29;
  assign T29 = T30[4:0];
  assign T30 = T31;
  assign T31 = T32;
  assign T32 = {1'h0, T19};
  assign T33 = T12 >> 1'h1;
  assign T34 = $signed(T30) < $signed(9'h82);
  assign T35 = T41 | T36;
  assign T36 = 8'h0 - T46;
  assign T46 = {7'h0, T37};
  assign T37 = T38 | T20;
  assign T38 = T39;
  assign T39 = T24 & T40;
  assign T40 = T19[6];
  assign T41 = T34 ? 8'h0 : T42;
  assign T42 = T43 - 8'h81;
  assign T43 = T30[7:0];
  assign T44 = T45;
  assign T45 = io_in[32];
endmodule

RecF32ToF32/trace.vcd
$version Generated by VerilatedVcd $end
$date Wed Jun  6 13:09:36 2018
 $end
$timescale   1ns $end

 $scope module TOP $end
  $var wire 24 / io_compare [23:0] $end
  $var wire  3 - io_firstThree [2:0] $end
  $var wire 33 ) io_in [32:0] $end
  $var wire  1 , io_isBadNaN $end
  $var wire 32 + io_out [31:0] $end
  $var wire 24 . io_sig [23:0] $end
  $scope module Equiv_RecF32ToF32 $end
   $var wire 24 0 T0 [23:0] $end
   $var wire  3 1 T1 [2:0] $end
   $var wire 23 # T10 [22:0] $end
   $var wire 23 $ T11 [22:0] $end
   $var wire 25 % T12 [24:0] $end
   $var wire 25 % T13 [24:0] $end
   $var wire 24 & T14 [23:0] $end
   $var wire 23 8 T15 [22:0] $end
   $var wire  1 9 T16 $end
   $var wire  1 : T17 $end
   $var wire  3 ; T18 [2:0] $end
   $var wire  9 < T19 [8:0] $end
   $var wire  1 2 T2 $end
   $var wire  1 ' T20 $end
   $var wire  1 ' T21 $end
   $var wire  1 = T22 $end
   $var wire  1 > T23 $end
   $var wire  1 ? T24 $end
   $var wire  2 @ T25 [1:0] $end
   $var wire 23 A T26 [22:0] $end
   $var wire 24 B T27 [23:0] $end
   $var wire  5 C T28 [4:0] $end
   $var wire  5 D T29 [4:0] $end
   $var wire  1 3 T3 $end
   $var wire 10 E T30 [9:0] $end
   $var wire 10 E T31 [9:0] $end
   $var wire 10 E T32 [9:0] $end
   $var wire 24 ( T33 [23:0] $end
   $var wire  1 F T34 $end
   $var wire  8 G T35 [7:0] $end
   $var wire  8 H T36 [7:0] $end
   $var wire  1 J T37 $end
   $var wire  1 K T38 $end
   $var wire  1 K T39 $end
   $var wire 24 0 T4 [23:0] $end
   $var wire  1 > T40 $end
   $var wire  8 L T41 [7:0] $end
   $var wire  8 M T42 [7:0] $end
   $var wire  8 N T43 [7:0] $end
   $var wire  1 O T44 $end
   $var wire  1 O T45 $end
   $var wire  8 I T46 [7:0] $end
   $var wire  1 4 T5 $end
   $var wire  3 1 T6 [2:0] $end
   $var wire 32 5 T7 [31:0] $end
   $var wire 31 6 T8 [30:0] $end
   $var wire 23 7 T9 [22:0] $end
   $var wire 24 / io_compare [23:0] $end
   $var wire  3 - io_firstThree [2:0] $end
   $var wire 33 ) io_in [32:0] $end
   $var wire  1 , io_isBadNaN $end
   $var wire 32 + io_out [31:0] $end
   $var wire 24 . io_sig [23:0] $end
  $upscope $end
 $upscope $end
$enddefinitions $end


#0
b11111111111111111111111 #
b11111111111111111111111 $
b0111111111111111111111111 %
b111111111111111111111111 &
0'
b011111111111111111111111 (
b000110101011111111111111111111111 )
b00000000000000000000000000000000 +
0,
b001 -
b011111111111111111111111 .
b111111111111111111111111 /
b011111111111111111111111 0
b001 1
02
13
04
b00000000000000000000000000000000 5
b0000000000000000000000000000000 6
b00000000000000000000000 7
b11111111111111111111111 8
19
0:
b001 ;
b001101010 <
0=
1>
0?
b00 @
b00000000000000000000000 A
b000000000000000000000000 B
b10111 C
b01010 D
b0001101010 E
1F
b00000000 G
b00000000 H
b00000000 I
0J
0K
b00000000 L
b11101001 M
b01101010 N
0O
#1
b000110100111111111111111111111111 )
b111111111111111111111111 .
b111111111111111111111111 0
03
b001101001 <
b11000 C
b01001 D
b0001101001 E
b11101000 M
b01101001 N
#2
b000110100011111111111111111111111 )
b011111111111111111111111 .
b011111111111111111111111 0
13
b001101000 <
b11001 C
b01000 D
b0001101000 E
b11100111 M
b01101000 N
#3
b000110011111111111111111111111111 )
b111111111111111111111111 .
b111111111111111111111111 0
03
b001100111 <
b11010 C
b00111 D
b0001100111 E
b11100110 M
b01100111 N
#4
b000110011011111111111111111111111 )
b011111111111111111111111 .
b011111111111111111111111 0
13
b001100110 <
b11011 C
b00110 D
b0001100110 E
b11100101 M
b01100110 N
#5
b000110010111111111111111111111111 )
b111111111111111111111111 .
b111111111111111111111111 0
03
b001100101 <
b11100 C
b00101 D
b0001100101 E
b11100100 M
b01100101 N
#6
b000110010011111111111111111111111 )
b011111111111111111111111 .
b011111111111111111111111 0
13
b001100100 <
b11101 C
b00100 D
b0001100100 E
b11100011 M
b01100100 N
#7
b000110001111111111111111111111111 )
b111111111111111111111111 .
b111111111111111111111111 0
03
b001100011 <
b11110 C
b00011 D
b0001100011 E
b11100010 M
b01100011 N
#8
b000110001011111111111111111111111 )
b011111111111111111111111 .
b011111111111111111111111 0
13
b001100010 <
b11111 C
b00010 D
b0001100010 E
b11100001 M
b01100010 N
#9
b000110000111111111111111111111111 )
b00000000011111111111111111111111 +
b111111111111111111111111 .
b111111111111111111111111 0
03
b00000000011111111111111111111111 5
b0000000011111111111111111111111 6
b11111111111111111111111 7
b001100001 <
b11111111111111111111111 A
b011111111111111111111111 B
b00000 C
b00001 D
b0001100001 E
b11100000 M
b01100001 N
#10
b000110000011111111111111111111111 )
b00000000001111111111111111111111 +
b011111111111111111111111 .
b011111111111111111111111 0
13
b00000000001111111111111111111111 5
b0000000001111111111111111111111 6
b01111111111111111111111 7
b001100000 <
b01111111111111111111111 A
b001111111111111111111111 B
b00001 C
b00000 D
b0001100000 E
b11011111 M
b01100000 N
#11
b000101111111111111111111111111111 )
b00000000000111111111111111111111 +
b111111111111111111111111 .
b111111111111111111111111 0
03
b00000000000111111111111111111111 5
b0000000000111111111111111111111 6
b00111111111111111111111 7
b001011111 <
b00111111111111111111111 A
b000111111111111111111111 B
b00010 C
b11111 D
b0001011111 E
b11011110 M
b01011111 N
#12
b000101111011111111111111111111111 )
b00000000000011111111111111111111 +
b011111111111111111111111 .
b011111111111111111111111 0
13
b00000000000011111111111111111111 5
b0000000000011111111111111111111 6
b00011111111111111111111 7
b001011110 <
b00011111111111111111111 A
b000011111111111111111111 B
b00011 C
b11110 D
b0001011110 E
b11011101 M
b01011110 N
#13
b000101110111111111111111111111111 )
b00000000000001111111111111111111 +
b111111111111111111111111 .
b111111111111111111111111 0
03
b00000000000001111111111111111111 5
b0000000000001111111111111111111 6
b00001111111111111111111 7
b001011101 <
b00001111111111111111111 A
b000001111111111111111111 B
b00100 C
b11101 D
b0001011101 E
b11011100 M
b01011101 N
#14
b000101110011111111111111111111111 )
b00000000000000111111111111111111 +
b011111111111111111111111 .
b011111111111111111111111 0
13
b00000000000000111111111111111111 5
b0000000000000111111111111111111 6
b00000111111111111111111 7
b001011100 <
b00000111111111111111111 A
b000000111111111111111111 B
b00101 C
b11100 D
b0001011100 E
b11011011 M
b01011100 N
#15
b000101101111111111111111111111111 )
b00000000000000011111111111111111 +
b111111111111111111111111 .
b111111111111111111111111 0
03
b00000000000000011111111111111111 5
b0000000000000011111111111111111 6
b00000011111111111111111 7
b001011011 <
b00000011111111111111111 A
b000000011111111111111111 B
b00110 C
b11011 D
b0001011011 E
b11011010 M
b01011011 N
#16
b000101101011111111111111111111111 )
b00000000000000001111111111111111 +
b011111111111111111111111 .
b011111111111111111111111 0
13
b00000000000000001111111111111111 5
b0000000000000001111111111111111 6
b00000001111111111111111 7
b001011010 <
b00000001111111111111111 A
b000000001111111111111111 B
b00111 C
b11010 D
b0001011010 E
b11011001 M
b01011010 N
#17
b000101100111111111111111111111111 )
b00000000000000000111111111111111 +
b111111111111111111111111 .
b111111111111111111111111 0
03
b00000000000000000111111111111111 5
b0000000000000000111111111111111 6
b00000000111111111111111 7
b001011001 <
b00000000111111111111111 A
b000000000111111111111111 B
b01000 C
b11001 D
b0001011001 E
b11011000 M
b01011001 N
#18
b000101100011111111111111111111111 )
b00000000000000000011111111111111 +
b011111111111111111111111 .
b011111111111111111111111 0
13
b00000000000000000011111111111111 5
b0000000000000000011111111111111 6
b00000000011111111111111 7
b001011000 <
b00000000011111111111111 A
b000000000011111111111111 B
b01001 C
b11000 D
b0001011000 E
b11010111 M
b01011000 N
#19
b000101011111111111111111111111111 )
b00000000000000000001111111111111 +
b111111111111111111111111 .
b111111111111111111111111 0
03
b00000000000000000001111111111111 5
b0000000000000000001111111111111 6
b00000000001111111111111 7
b001010111 <
b00000000001111111111111 A
b000000000001111111111111 B
b01010 C
b10111 D
b0001010111 E
b11010110 M
b01010111 N
#20
b000101011011111111111111111111111 )
b00000000000000000000111111111111 +
b011111111111111111111111 .
b011111111111111111111111 0
13
b00000000000000000000111111111111 5
b0000000000000000000111111111111 6
b00000000000111111111111 7
b001010110 <
b00000000000111111111111 A
b000000000000111111111111 B
b01011 C
b10110 D
b0001010110 E
b11010101 M
b01010110 N
#21
b000101010111111111111111111111111 )
b00000000000000000000011111111111 +
b111111111111111111111111 .
b111111111111111111111111 0
03
b00000000000000000000011111111111 5
b0000000000000000000011111111111 6
b00000000000011111111111 7
b001010101 <
b00000000000011111111111 A
b000000000000011111111111 B
b01100 C
b10101 D
b0001010101 E
b11010100 M
b01010101 N
#22
b000101010011111111111111111111111 )
b00000000000000000000001111111111 +
b011111111111111111111111 .
b011111111111111111111111 0
13
b00000000000000000000001111111111 5
b0000000000000000000001111111111 6
b00000000000001111111111 7
b001010100 <
b00000000000001111111111 A
b000000000000001111111111 B
b01101 C
b10100 D
b0001010100 E
b11010011 M
b01010100 N
#23
b000101001111111111111111111111111 )
b00000000000000000000000111111111 +
b111111111111111111111111 .
b111111111111111111111111 0
03
b00000000000000000000000111111111 5
b0000000000000000000000111111111 6
b00000000000000111111111 7
b001010011 <
b00000000000000111111111 A
b000000000000000111111111 B
b01110 C
b10011 D
b0001010011 E
b11010010 M
b01010011 N
#24
b000101001011111111111111111111111 )
b00000000000000000000000011111111 +
b011111111111111111111111 .
b011111111111111111111111 0
13
b00000000000000000000000011111111 5
b0000000000000000000000011111111 6
b00000000000000011111111 7
b001010010 <
b00000000000000011111111 A
b000000000000000011111111 B
b01111 C
b10010 D
b0001010010 E
b11010001 M
b01010010 N
#25
b000101000111111111111111111111111 )
b00000000000000000000000001111111 +
b111111111111111111111111 .
b111111111111111111111111 0
03
b00000000000000000000000001111111 5
b0000000000000000000000001111111 6
b00000000000000001111111 7
b001010001 <
b00000000000000001111111 A
b000000000000000001111111 B
b10000 C
b10001 D
b0001010001 E
b11010000 M
b01010001 N
#26
b000101000011111111111111111111111 )
b00000000000000000000000000111111 +
b011111111111111111111111 .
b011111111111111111111111 0
13
b00000000000000000000000000111111 5
b0000000000000000000000000111111 6
b00000000000000000111111 7
b001010000 <
b00000000000000000111111 A
b000000000000000000111111 B
b10001 C
b10000 D
b0001010000 E
b11001111 M
b01010000 N
#27
b000100111111111111111111111111111 )
b00000000000000000000000000011111 +
b111111111111111111111111 .
b111111111111111111111111 0
03
b00000000000000000000000000011111 5
b0000000000000000000000000011111 6
b00000000000000000011111 7
b001001111 <
b00000000000000000011111 A
b000000000000000000011111 B
b10010 C
b01111 D
b0001001111 E
b11001110 M
b01001111 N
#28
b000100111011111111111111111111111 )
b00000000000000000000000000001111 +
b011111111111111111111111 .
b011111111111111111111111 0
13
b00000000000000000000000000001111 5
b0000000000000000000000000001111 6
b00000000000000000001111 7
b001001110 <
b00000000000000000001111 A
b000000000000000000001111 B
b10011 C
b01110 D
b0001001110 E
b11001101 M
b01001110 N
#29
b000100110111111111111111111111111 )
b00000000000000000000000000000111 +
b111111111111111111111111 .
b111111111111111111111111 0
03
b00000000000000000000000000000111 5
b0000000000000000000000000000111 6
b00000000000000000000111 7
b001001101 <
b00000000000000000000111 A
b000000000000000000000111 B
b10100 C
b01101 D
b0001001101 E
b11001100 M
b01001101 N
#30
b000100110011111111111111111111111 )
b00000000000000000000000000000011 +
b011111111111111111111111 .
b011111111111111111111111 0
13
b00000000000000000000000000000011 5
b0000000000000000000000000000011 6
b00000000000000000000011 7
b001001100 <
b00000000000000000000011 A
b000000000000000000000011 B
b10101 C
b01100 D
b0001001100 E
b11001011 M
b01001100 N
#31
b000100101111111111111111111111111 )
b00000000000000000000000000000001 +
b111111111111111111111111 .
b111111111111111111111111 0
03
b00000000000000000000000000000001 5
b0000000000000000000000000000001 6
b00000000000000000000001 7
b001001011 <
b00000000000000000000001 A
b000000000000000000000001 B
b10110 C
b01011 D
b0001001011 E
b11001010 M
b01001011 N
#32
b000100101011111111111111111111111 )
b00000000000000000000000000000000 +
b011111111111111111111111 .
b011111111111111111111111 0
13
b00000000000000000000000000000000 5
b0000000000000000000000000000000 6
b00000000000000000000000 7
b001001010 <
b00000000000000000000000 A
b000000000000000000000000 B
b10111 C
b01010 D
b0001001010 E
b11001001 M
b01001010 N
#33
b000100100111111111111111111111111 )
b111111111111111111111111 .
b111111111111111111111111 0
03
b001001001 <
b11000 C
b01001 D
b0001001001 E
b11001000 M
b01001001 N
#34
b000100100011111111111111111111111 )
b011111111111111111111111 .
b011111111111111111111111 0
13
b001001000 <
b11001 C
b01000 D
b0001001000 E
b11000111 M
b01001000 N
#35
b000100011111111111111111111111111 )
b111111111111111111111111 .
b111111111111111111111111 0
03
b001000111 <
b11010 C
b00111 D
b0001000111 E
b11000110 M
b01000111 N
#36
b000100011011111111111111111111111 )
b011111111111111111111111 .
b011111111111111111111111 0
13
b001000110 <
b11011 C
b00110 D
b0001000110 E
b11000101 M
b01000110 N
#37
b000100010111111111111111111111111 )
b111111111111111111111111 .
b111111111111111111111111 0
03
b001000101 <
b11100 C
b00101 D
b0001000101 E
b11000100 M
b01000101 N
#38
b000100010011111111111111111111111 )
b011111111111111111111111 .
b011111111111111111111111 0
13
b001000100 <
b11101 C
b00100 D
b0001000100 E
b11000011 M
b01000100 N
#39
b000100001111111111111111111111111 )
b111111111111111111111111 .
b111111111111111111111111 0
03
b001000011 <
b11110 C
b00011 D
b0001000011 E
b11000010 M
b01000011 N
#40
b000100001011111111111111111111111 )
b011111111111111111111111 .
b011111111111111111111111 0
13
b001000010 <
b11111 C
b00010 D
b0001000010 E
b11000001 M
b01000010 N
#41
b000100000111111111111111111111111 )
b00000000011111111111111111111111 +
b111111111111111111111111 .
b111111111111111111111111 0
03
b00000000011111111111111111111111 5
b0000000011111111111111111111111 6
b11111111111111111111111 7
b001000001 <
b11111111111111111111111 A
b011111111111111111111111 B
b00000 C
b00001 D
b0001000001 E
b11000000 M
b01000001 N
#42
b000100000011111111111111111111111 )
b00000000001111111111111111111111 +
b011111111111111111111111 .
b011111111111111111111111 0
13
b00000000001111111111111111111111 5
b0000000001111111111111111111111 6
b01111111111111111111111 7
b001000000 <
b01111111111111111111111 A
b001111111111111111111111 B
b00001 C
b00000 D
b0001000000 E
b10111111 M
b01000000 N
#43
b0011111111111111111111111 %
b011111111111111111111111 &
b001111111111111111111111 (
b000011111111111111111111111111111 )
b00000000000011111111111111111111 +
b000 -
b111111111111111111111111 .
b111111111111111111111111 0
b000 1
03
b00000000000011111111111111111111 5
b0000000000011111111111111111111 6
b00011111111111111111111 7
09
1:
b000 ;
b000111111 <
1=
0>
b00011111111111111111111 A
b000011111111111111111111 B
b00010 C
b11111 D
b0000111111 E
b10111110 M
b00111111 N
#44
b000011111011111111111111111111111 )
b00000000000001111111111111111111 +
b011111111111111111111111 .
b011111111111111111111111 0
13
b00000000000001111111111111111111 5
b0000000000001111111111111111111 6
b00001111111111111111111 7
b000111110 <
b00001111111111111111111 A
b000001111111111111111111 B
b00011 C
b11110 D
b0000111110 E
b10111101 M
b00111110 N
#45
b000011110111111111111111111111111 )
b00000000000000111111111111111111 +
b111111111111111111111111 .
b111111111111111111111111 0
03
b00000000000000111111111111111111 5
b0000000000000111111111111111111 6
b00000111111111111111111 7
b000111101 <
b00000111111111111111111 A
b000000111111111111111111 B
b00100 C
b11101 D
b0000111101 E
b10111100 M
b00111101 N
#46
b000011110011111111111111111111111 )
b00000000000000011111111111111111 +
b011111111111111111111111 .
b011111111111111111111111 0
13
b00000000000000011111111111111111 5
b0000000000000011111111111111111 6
b00000011111111111111111 7
b000111100 <
b00000011111111111111111 A
b000000011111111111111111 B
b00101 C
b11100 D
b0000111100 E
b10111011 M
b00111100 N
#47
b000011101111111111111111111111111 )
b00000000000000001111111111111111 +
b111111111111111111111111 .
b111111111111111111111111 0
03
b00000000000000001111111111111111 5
b0000000000000001111111111111111 6
b00000001111111111111111 7
b000111011 <
b00000001111111111111111 A
b000000001111111111111111 B
b00110 C
b11011 D
b0000111011 E
b10111010 M
b00111011 N
#48
b000011101011111111111111111111111 )
b00000000000000000111111111111111 +
b011111111111111111111111 .
b011111111111111111111111 0
13
b00000000000000000111111111111111 5
b0000000000000000111111111111111 6
b00000000111111111111111 7
b000111010 <
b00000000111111111111111 A
b000000000111111111111111 B
b00111 C
b11010 D
b0000111010 E
b10111001 M
b00111010 N
#49
b000011100111111111111111111111111 )
b00000000000000000011111111111111 +
b111111111111111111111111 .
b111111111111111111111111 0
03
b00000000000000000011111111111111 5
b0000000000000000011111111111111 6
b00000000011111111111111 7
b000111001 <
b00000000011111111111111 A
b000000000011111111111111 B
b01000 C
b11001 D
b0000111001 E
b10111000 M
b00111001 N
#50
b000011100011111111111111111111111 )
b00000000000000000001111111111111 +
b011111111111111111111111 .
b011111111111111111111111 0
13
b00000000000000000001111111111111 5
b0000000000000000001111111111111 6
b00000000001111111111111 7
b000111000 <
b00000000001111111111111 A
b000000000001111111111111 B
b01001 C
b11000 D
b0000111000 E
b10110111 M
b00111000 N
#51
b000011011111111111111111111111111 )
b00000000000000000000111111111111 +
b111111111111111111111111 .
b111111111111111111111111 0
03
b00000000000000000000111111111111 5
b0000000000000000000111111111111 6
b00000000000111111111111 7
b000110111 <
b00000000000111111111111 A
b000000000000111111111111 B
b01010 C
b10111 D
b0000110111 E
b10110110 M
b00110111 N
#52
b000011011011111111111111111111111 )
b00000000000000000000011111111111 +
b011111111111111111111111 .
b011111111111111111111111 0
13
b00000000000000000000011111111111 5
b0000000000000000000011111111111 6
b00000000000011111111111 7
b000110110 <
b00000000000011111111111 A
b000000000000011111111111 B
b01011 C
b10110 D
b0000110110 E
b10110101 M
b00110110 N
#53
b000011010111111111111111111111111 )
b00000000000000000000001111111111 +
b111111111111111111111111 .
b111111111111111111111111 0
03
b00000000000000000000001111111111 5
b0000000000000000000001111111111 6
b00000000000001111111111 7
b000110101 <
b00000000000001111111111 A
b000000000000001111111111 B
b01100 C
b10101 D
b0000110101 E
b10110100 M
b00110101 N
#54
b000011010011111111111111111111111 )
b00000000000000000000000111111111 +
b011111111111111111111111 .
b011111111111111111111111 0
13
b00000000000000000000000111111111 5
b0000000000000000000000111111111 6
b00000000000000111111111 7
b000110100 <
b00000000000000111111111 A
b000000000000000111111111 B
b01101 C
b10100 D
b0000110100 E
b10110011 M
b00110100 N
#55
b000011001111111111111111111111111 )
b00000000000000000000000011111111 +
b111111111111111111111111 .
b111111111111111111111111 0
03
b00000000000000000000000011111111 5
b0000000000000000000000011111111 6
b00000000000000011111111 7
b000110011 <
b00000000000000011111111 A
b000000000000000011111111 B
b01110 C
b10011 D
b0000110011 E
b10110010 M
b00110011 N
#56
b000011001011111111111111111111111 )
b00000000000000000000000001111111 +
b011111111111111111111111 .
b011111111111111111111111 0
13
b00000000000000000000000001111111 5
b0000000000000000000000001111111 6
b00000000000000001111111 7
b000110010 <
b00000000000000001111111 A
b000000000000000001111111 B
b01111 C
b10010 D
b0000110010 E
b10110001 M
b00110010 N
#57
b000011000111111111111111111111111 )
b00000000000000000000000000111111 +
b111111111111111111111111 .
b111111111111111111111111 0
03
b00000000000000000000000000111111 5
b0000000000000000000000000111111 6
b00000000000000000111111 7
b000110001 <
b00000000000000000111111 A
b000000000000000000111111 B
b10000 C
b10001 D
b0000110001 E
b10110000 M
b00110001 N
#58
b000011000011111111111111111111111 )
b00000000000000000000000000011111 +
b011111111111111111111111 .
b011111111111111111111111 0
13
b00000000000000000000000000011111 5
b0000000000000000000000000011111 6
b00000000000000000011111 7
b000110000 <
b00000000000000000011111 A
b000000000000000000011111 B
b10001 C
b10000 D
b0000110000 E
b10101111 M
b00110000 N
#59
b000010111111111111111111111111111 )
b00000000000000000000000000001111 +
b111111111111111111111111 .
b111111111111111111111111 0
03
b00000000000000000000000000001111 5
b0000000000000000000000000001111 6
b00000000000000000001111 7
b000101111 <
b00000000000000000001111 A
b000000000000000000001111 B
b10010 C
b01111 D
b0000101111 E
b10101110 M
b00101111 N
#60
b000010111011111111111111111111111 )
b00000000000000000000000000000111 +
b011111111111111111111111 .
b011111111111111111111111 0
13
b00000000000000000000000000000111 5
b0000000000000000000000000000111 6
b00000000000000000000111 7
b000101110 <
b00000000000000000000111 A
b000000000000000000000111 B
b10011 C
b01110 D
b0000101110 E
b10101101 M
b00101110 N
#61
b000010110111111111111111111111111 )
b00000000000000000000000000000011 +
b111111111111111111111111 .
b111111111111111111111111 0
03
b00000000000000000000000000000011 5
b0000000000000000000000000000011 6
b00000000000000000000011 7
b000101101 <
b00000000000000000000011 A
b000000000000000000000011 B
b10100 C
b01101 D
b0000101101 E
b10101100 M
b00101101 N
#62
b000010110011111111111111111111111 )
b00000000000000000000000000000001 +
b011111111111111111111111 .
b011111111111111111111111 0
13
b00000000000000000000000000000001 5
b0000000000000000000000000000001 6
b00000000000000000000001 7
b000101100 <
b00000000000000000000001 A
b000000000000000000000001 B
b10101 C
b01100 D
b0000101100 E
b10101011 M
b00101100 N
#63
b000010101111111111111111111111111 )
b00000000000000000000000000000000 +
b111111111111111111111111 .
b111111111111111111111111 0
03
b00000000000000000000000000000000 5
b0000000000000000000000000000000 6
b00000000000000000000000 7
b000101011 <
b00000000000000000000000 A
b000000000000000000000000 B
b10110 C
b01011 D
b0000101011 E
b10101010 M
b00101011 N
#64
b000010101011111111111111111111111 )
b011111111111111111111111 .
b011111111111111111111111 0
13
b000101010 <
b10111 C
b01010 D
b0000101010 E
b10101001 M
b00101010 N
#65
b000010100111111111111111111111111 )
b111111111111111111111111 .
b111111111111111111111111 0
03
b000101001 <
b11000 C
b01001 D
b0000101001 E
b10101000 M
b00101001 N
#66
b000010100011111111111111111111111 )
b011111111111111111111111 .
b011111111111111111111111 0
13
b000101000 <
b11001 C
b01000 D
b0000101000 E
b10100111 M
b00101000 N
#67
b000010011111111111111111111111111 )
b111111111111111111111111 .
b111111111111111111111111 0
03
b000100111 <
b11010 C
b00111 D
b0000100111 E
b10100110 M
b00100111 N
#68
b000010011011111111111111111111111 )
b011111111111111111111111 .
b011111111111111111111111 0
13
b000100110 <
b11011 C
b00110 D
b0000100110 E
b10100101 M
b00100110 N
#69
b000010010111111111111111111111111 )
b111111111111111111111111 .
b111111111111111111111111 0
03
b000100101 <
b11100 C
b00101 D
b0000100101 E
b10100100 M
b00100101 N
#70
b000010010011111111111111111111111 )
b011111111111111111111111 .
b011111111111111111111111 0
13
b000100100 <
b11101 C
b00100 D
b0000100100 E
b10100011 M
b00100100 N
#71
b000010001111111111111111111111111 )
b111111111111111111111111 .
b111111111111111111111111 0
03
b000100011 <
b11110 C
b00011 D
b0000100011 E
b10100010 M
b00100011 N
#72
b000010001011111111111111111111111 )
b011111111111111111111111 .
b011111111111111111111111 0
13
b000100010 <
b11111 C
b00010 D
b0000100010 E
b10100001 M
b00100010 N
#73
b000010000111111111111111111111111 )
b00000000001111111111111111111111 +
b111111111111111111111111 .
b111111111111111111111111 0
03
b00000000001111111111111111111111 5
b0000000001111111111111111111111 6
b01111111111111111111111 7
b000100001 <
b01111111111111111111111 A
b001111111111111111111111 B
b00000 C
b00001 D
b0000100001 E
b10100000 M
b00100001 N
#74
b000010000011111111111111111111111 )
b00000000000111111111111111111111 +
b011111111111111111111111 .
b011111111111111111111111 0
13
b00000000000111111111111111111111 5
b0000000000111111111111111111111 6
b00111111111111111111111 7
b000100000 <
b00111111111111111111111 A
b000111111111111111111111 B
b00001 C
b00000 D
b0000100000 E
b10011111 M
b00100000 N
#75
b000001111111111111111111111111111 )
b00000000000011111111111111111111 +
b111111111111111111111111 .
b111111111111111111111111 0
03
b00000000000011111111111111111111 5
b0000000000011111111111111111111 6
b00011111111111111111111 7
b000011111 <
b00011111111111111111111 A
b000011111111111111111111 B
b00010 C
b11111 D
b0000011111 E
b10011110 M
b00011111 N
#76
b000001111011111111111111111111111 )
b00000000000001111111111111111111 +
b011111111111111111111111 .
b011111111111111111111111 0
13
b00000000000001111111111111111111 5
b0000000000001111111111111111111 6
b00001111111111111111111 7
b000011110 <
b00001111111111111111111 A
b000001111111111111111111 B
b00011 C
b11110 D
b0000011110 E
b10011101 M
b00011110 N
#77
b000001110111111111111111111111111 )
b00000000000000111111111111111111 +
b111111111111111111111111 .
b111111111111111111111111 0
03
b00000000000000111111111111111111 5
b0000000000000111111111111111111 6
b00000111111111111111111 7
b000011101 <
b00000111111111111111111 A
b000000111111111111111111 B
b00100 C
b11101 D
b0000011101 E
b10011100 M
b00011101 N
#78
b000001110011111111111111111111111 )
b00000000000000011111111111111111 +
b011111111111111111111111 .
b011111111111111111111111 0
13
b00000000000000011111111111111111 5
b0000000000000011111111111111111 6
b00000011111111111111111 7
b000011100 <
b00000011111111111111111 A
b000000011111111111111111 B
b00101 C
b11100 D
b0000011100 E
b10011011 M
b00011100 N
#79
b000001101111111111111111111111111 )
b00000000000000001111111111111111 +
b111111111111111111111111 .
b111111111111111111111111 0
03
b00000000000000001111111111111111 5
b0000000000000001111111111111111 6
b00000001111111111111111 7
b000011011 <
b00000001111111111111111 A
b000000001111111111111111 B
b00110 C
b11011 D
b0000011011 E
b10011010 M
b00011011 N
#80
b000001101011111111111111111111111 )
b00000000000000000111111111111111 +
b011111111111111111111111 .
b011111111111111111111111 0
13
b00000000000000000111111111111111 5
b0000000000000000111111111111111 6
b00000000111111111111111 7
b000011010 <
b00000000111111111111111 A
b000000000111111111111111 B
b00111 C
b11010 D
b0000011010 E
b10011001 M
b00011010 N
#81
b000001100111111111111111111111111 )
b00000000000000000011111111111111 +
b111111111111111111111111 .
b111111111111111111111111 0
03
b00000000000000000011111111111111 5
b0000000000000000011111111111111 6
b00000000011111111111111 7
b000011001 <
b00000000011111111111111 A
b000000000011111111111111 B
b01000 C
b11001 D
b0000011001 E
b10011000 M
b00011001 N
#82
b000001100011111111111111111111111 )
b00000000000000000001111111111111 +
b011111111111111111111111 .
b011111111111111111111111 0
13
b00000000000000000001111111111111 5
b0000000000000000001111111111111 6
b00000000001111111111111 7
b000011000 <
b00000000001111111111111 A
b000000000001111111111111 B
b01001 C
b11000 D
b0000011000 E
b10010111 M
b00011000 N
#83
b000001011111111111111111111111111 )
b00000000000000000000111111111111 +
b111111111111111111111111 .
b111111111111111111111111 0
03
b00000000000000000000111111111111 5
b0000000000000000000111111111111 6
b00000000000111111111111 7
b000010111 <
b00000000000111111111111 A
b000000000000111111111111 B
b01010 C
b10111 D
b0000010111 E
b10010110 M
b00010111 N
